datamimic_ce/__init__.py
datamimic_ce/cli.py
datamimic_ce/config.py
datamimic_ce/data_mimic_test.py
datamimic_ce/datamimic.py
datamimic_ce/clients/__init__.py
datamimic_ce/clients/client.py
datamimic_ce/clients/database_client.py
datamimic_ce/clients/mongodb_client.py
datamimic_ce/clients/rdbms_client.py
datamimic_ce/connection_config/__init__.py
datamimic_ce/connection_config/connection_config_base.py
datamimic_ce/connection_config/mongodb_connection_config.py
datamimic_ce/connection_config/rdbms_connection_config.py
datamimic_ce/constants/__init__.py
datamimic_ce/constants/attribute_constants.py
datamimic_ce/constants/convention_constants.py
datamimic_ce/constants/data_type_constants.py
datamimic_ce/constants/element_constants.py
datamimic_ce/constants/exporter_constants.py
datamimic_ce/contexts/__init__.py
datamimic_ce/contexts/context.py
datamimic_ce/contexts/demographic_context.py
datamimic_ce/contexts/geniter_context.py
datamimic_ce/contexts/setup_context.py
datamimic_ce/converter/__init__.py
datamimic_ce/converter/append_converter.py
datamimic_ce/converter/converter.py
datamimic_ce/converter/converter_util.py
datamimic_ce/converter/custom_converter.py
datamimic_ce/converter/cut_length_converter.py
datamimic_ce/converter/date2timestamp_converter.py
datamimic_ce/converter/date_format_converter.py
datamimic_ce/converter/hash_converter.py
datamimic_ce/converter/java_hash_converter.py
datamimic_ce/converter/lower_case_converter.py
datamimic_ce/converter/mask_converter.py
datamimic_ce/converter/middle_mask_converter.py
datamimic_ce/converter/remove_none_or_empty_element_converter.py
datamimic_ce/converter/timestamp2date_converter.py
datamimic_ce/converter/upper_case_converter.py
datamimic_ce/data_sources/__init__.py
datamimic_ce/data_sources/data_source_pagination.py
datamimic_ce/data_sources/data_source_registry.py
datamimic_ce/data_sources/weighted_data_source.py
datamimic_ce/data_sources/weighted_entity_data_source.py
datamimic_ce/demos/__init___.py
datamimic_ce-2.2.0.dist-info/licenses/LICENSE
datamimic_ce-2.2.0.dist-info/METADATA
datamimic_ce-2.2.0.dist-info/WHEEL
datamimic_ce-2.2.0.dist-info/entry_points.txt
datamimic_ce-2.2.0.dist-info/top_level.txt
datamimic_ce-2.2.0.dist-info/RECORD
