Metadata-Version: 2.4
Name: datamimic_ce
Version: 2.2.0
Author-email: "Rapiddweller Asia Co., Ltd." <info@rapiddweller.com>
Project-URL: Homepage, https://datamimic.io
Keywords: datamimic,data,synthetic,generation,privacy,security,testing,modeling
Requires-Python: >=3.10
License-File: LICENSE
Requires-Dist: dill>=0.3.0
Requires-Dist: faker==33.3.1
Requires-Dist: mysql-connector-python==8.3.0
Requires-Dist: numpy>=1.26.3
Requires-Dist: oracledb==2.5.1
Requires-Dist: psycopg2-binary==2.9.10
Requires-Dist: pydantic==2.10.5
Requires-Dist: pydantic-settings==2.7.1
Requires-Dist: pydantic[email]
Requires-Dist: pymongo==4.10.1
Requires-Dist: pyodbc==5.2.0
Requires-Dist: python-dotenv==1.0.1
Requires-Dist: requests==2.32.3
Requires-Dist: sqlalchemy==2.0.37
Requires-Dist: xmltodict==0.14.2
Requires-Dist: pandas==2.2.3
Requires-Dist: toml>=0.10.2
Requires-Dist: typer>=0.12.5
Requires-Dist: psutil>=5.9.5
Requires-Dist: exrex>=0.12.0
Requires-Dist: lxml>=5.3.0
Requires-Dist: jsonschema>=4.23.0
Provides-Extra: ray
Requires-Dist: ray>=2.40.0; extra == "ray"
Provides-Extra: mcp
Requires-Dist: fastmcp>=2.0; extra == "mcp"
Requires-Dist: uvicorn>=0.30; extra == "mcp"
Dynamic: license-file
